[{
    "id": 30,
    "name": "Agua Con Gas 1,5 lts",
    "stock": 8,
    "price": 45,
    "pictureUrl": "https://dummyimage.com/450x300/dee2e6/6c757d.jpg"
  },
  {
    "id": 29,
    "name": "Agua Sin Gas 1,5 lts",
    "stock": 100,
    "price": 140,
    "pictureUrl": "https://dummyimage.com/450x300/dee2e6/6c757d.jpg"
  },
  {
    "id": 76,
    "name": "Alambrado Chardonnay 750 ml",
    "stock": 14,
    "price": 575,
    "pictureUrl": "https://dummyimage.com/450x300/dee2e6/6c757d.jpg"
  },
  {
    "id": 78,
    "name": "Alambrado Chardonnay 750 ml",
    "stock": 14,
    "price": 575,
    "pictureUrl": "https://dummyimage.com/450x300/dee2e6/6c757d.jpg"
  },
  {
    "id": 79,
    "name": "Alambrado Chardonnay 750 ml",
    "stock": 14,
    "price": 575,
    "pictureUrl": "https://dummyimage.com/450x300/dee2e6/6c757d.jpg"
  },
  {
    "id": 80,
    "name": "Alambrado Chardonnay 750 ml",
    "stock": 14,
    "price": 575,
    "pictureUrl": "https://dummyimage.com/450x300/dee2e6/6c757d.jpg"
  }
]